cardtale/__init__.py
cardtale/analytics/__init__.py
cardtale/analytics/operations/__init__.py
cardtale/analytics/operations/landmarking/__init__.py
cardtale/analytics/operations/landmarking/base.py
cardtale/analytics/operations/landmarking/change.py
cardtale/analytics/operations/landmarking/config.py
cardtale/analytics/operations/landmarking/seasonality.py
cardtale/analytics/operations/landmarking/trend.py
cardtale/analytics/operations/landmarking/variance.py
cardtale/analytics/operations/tsa/__init__.py
cardtale/analytics/operations/tsa/acf.py
cardtale/analytics/operations/tsa/change_points.py
cardtale/analytics/operations/tsa/decomposition.py
cardtale/analytics/operations/tsa/group_tests.py
cardtale/analytics/operations/tsa/heteroskedasticity.py
cardtale/analytics/operations/tsa/log.py
cardtale/analytics/operations/tsa/ndiffs.py
cardtale/analytics/operations/tsa/time_model.py
cardtale/analytics/testing/__init__.py
cardtale/analytics/testing/base.py
cardtale/analytics/testing/card/__init__.py
cardtale/analytics/testing/card/base.py
cardtale/analytics/testing/card/change.py
cardtale/analytics/testing/card/seasonality.py
cardtale/analytics/testing/card/trend.py
cardtale/analytics/testing/card/variance.py
cardtale/cards/__init__.py
cardtale/cards/builder.py
cardtale/cards/config.py
cardtale/cards/strings.py
cardtale/cards/cardset/__init__.py
cardtale/cards/cardset/base.py
cardtale/cards/cardset/change.py
cardtale/cards/cardset/seasonality.py
cardtale/cards/cardset/structural.py
cardtale/cards/cardset/trend.py
cardtale/cards/cardset/variance.py
cardtale/cards/templates/html/card.html
cardtale/cards/templates/html/structure.html
cardtale/cards/templates/strings/en-gb.json
cardtale/core/__init__.py
cardtale/core/data.py
cardtale/core/profile.py
cardtale/core/time.py
cardtale/core/config/__init__.py
cardtale/core/config/analysis.py
cardtale/core/config/freq.py
cardtale/core/config/typing.py
cardtale/core/utils/__init__.py
cardtale/core/utils/splits.py
cardtale-0.1.4.dist-info/METADATA
cardtale-0.1.4.dist-info/WHEEL
cardtale-0.1.4.dist-info/RECORD
