Metadata-Version: 2.4
Name: cardtale
Version: 0.1.4
Summary: Data, Model, and Algorithm Cards for Time Series
Project-URL: Homepage, https://github.com/vcerqueira/cardtale
Project-URL: Bug Tracker, https://github.com/vcerqueira/cardtale/issues
Author-email: Vitor Cerqueira <cerqueira.vitormanuel@gmail.com>
Keywords: Data Cards,Data Science,Forecasting,Machine Learning,Model Cards,Time Series
Classifier: License :: OSI Approved :: MIT License
Classifier: Operating System :: OS Independent
Classifier: Programming Language :: Python :: 3
Requires-Python: >=3.8
Requires-Dist: arch==7.1.0
Requires-Dist: datasetsforecast==0.0.8
Requires-Dist: jinja2==3.1.4
Requires-Dist: lightgbm==4.5.0
Requires-Dist: mlforecast==0.13.4
Requires-Dist: neuralforecast==3.0.0
Requires-Dist: numerize==0.12
Requires-Dist: pandas==2.2.3
Requires-Dist: plotnine==0.14.5
Requires-Dist: ruptures==1.1.9
Requires-Dist: statsforecast==1.7.8
Requires-Dist: statsmodels==0.14.4
Requires-Dist: weasyprint==62.3
